[{"address":"Home","address2":"","birthday":null,"city":"Home","country":"United States","date_joined":"2025-01-23 09:31:58.637185","email":"admin@admin.com","first_name":"admin","has_logged_in":1,"id":1,"is_active":1,"is_staff":1,"is_superuser":1,"last_login":"2025-02-02 09:34:36.449299","last_name":"admin","membership":100100,"membership_expiration":"3000-12-31","password":"pbkdf2_sha256$870000$TI33k4NwMP4J1WS8UJAzaJ$lLLRLnKAbtQhIqs1g58ujAqdlfs7GUanPcahIKNtkFA=","postal_code":"12345","state_province":"Oregon","username":"admin"},{"address":"9423 Louis Hills","address2":"Apt. 262","birthday":"2007-09-24","city":"West Michelle","country":"Canada","date_joined":"2025-01-23 09:31:58.641335","email":"Frank_Smith@samplemail.com","first_name":"Frank","has_logged_in":1,"id":2,"is_active":1,"is_staff":0,"is_superuser":0,"last_login":null,"last_name":"Smith","membership":null,"membership_expiration":null,"password":"pbkdf2_sha256$870000$CZXARgh8gStsh9m1yBGWVy$V2M4vTrB1uxK3L3YDUbYCK0/ambVqcaCmVWZ8u8Tyh8=","postal_code":"14876","state_province":"British Columbia","username":"Frank_Smith@samplemail.com"},{"address":"5984 Madeline Burg","address2":"","birthday":"2000-03-10","city":"Olsonhaven","country":"United States","date_joined":"2025-01-23 09:31:58.645451","email":"hernandezgary@gmail.com","first_name":"Melinda","has_logged_in":1,"id":3,"is_active":1,"is_staff":0,"is_superuser":0,"last_login":"2025-02-02 09:36:05.635449","last_name":"Henry","membership":11487986,"membership_expiration":"2028-05-15","password":"pbkdf2_sha256$870000$xF9kCeNOfEPZqXTgQsRShv$zG6kCRmGZ+O1zNURKyROm43CNiSdSvg6pC17YaKj65g=","postal_code":"65689","state_province":"Oregon","username":"hernandezgary@gmail.com"},{"address":"8186 Teresa Drive","address2":"","birthday":null,"city":"Perkinsview","country":"United States","date_joined":"2025-01-23 09:31:58.649573","email":"millscharles@blackburn.com","first_name":"Lisa","has_logged_in":1,"id":4,"is_active":1,"is_staff":0,"is_superuser":0,"last_login":null,"last_name":"Nunez","membership":98248406,"membership_expiration":"2026-12-13","password":"pbkdf2_sha256$870000$QMBiaUtPKjBY6c1L4UjDC7$SAT/h72wrH0bckk/XSTgROleoJO9Tg4gSNHtl6pzm4Y=","postal_code":"55267","state_province":"Washington","username":"millscharles@blackburn.com"},{"address":"32533 Martinez Ferry","address2":"","birthday":null,"city":"North Debrastad","country":"Canada","date_joined":"2025-01-23 09:31:58.653725","email":"anna43@gmail.com","first_name":"Karen","has_logged_in":1,"id":5,"is_active":1,"is_staff":0,"is_superuser":0,"last_login":"2025-02-02 09:37:50.635043","last_name":"Wade","membership":42358140,"membership_expiration":"2026-05-11","password":"pbkdf2_sha256$870000$z35fnVy4OEebninjQMgF1U$MSndlgLb7JHfqrWuD+AzPbQwzJZJQ1Nqb3CVvaimt3Y=","postal_code":"46979","state_province":"British Columbia","username":"anna43@gmail.com"},{"address":"1477 Holden Radial Apt. 865","address2":"","birthday":"2000-09-13","city":"Lake Johntown","country":"United States","date_joined":"2025-01-23 09:31:58.657866","email":"gmoore@hotmail.com","first_name":"Nicole","has_logged_in":1,"id":6,"is_active":1,"is_staff":0,"is_superuser":0,"last_login":null,"last_name":"Hawkins","membership":68370965,"membership_expiration":"2024-02-02","password":"pbkdf2_sha256$870000$dqi0KkTrdmNGhesbBFqMDQ$Jntx4MeKZG35EwdFk+FUuLqoHdANr6aAezSkWbCRCWA=","postal_code":"11548","state_province":"Oregon","username":"gmoore@hotmail.com"},{"address":"95406 Vasquez Neck Suite 544","address2":"","birthday":null,"city":"Hamptonstad","country":"United States","date_joined":"2025-01-23 09:31:58.661480","email":"rdonaldson@foster.net","first_name":"Andrea","has_logged_in":1,"id":7,"is_active":1,"is_staff":0,"is_superuser":0,"last_login":null,"last_name":"Mahoney","membership":15280790,"membership_expiration":"2025-01-13","password":"pbkdf2_sha256$870000$VYAAs6WvcJs7aFav54JVzO$U0rdjZvQaB5euPaUF0LFLw6ZKpfUqglzXXBB14oI9dA=","postal_code":"12021","state_province":"Washington","username":"rdonaldson@foster.net"},{"address":"113 Cole Terrace","address2":"","birthday":"2009-04-19","city":"Ashleymouth","country":"United States","date_joined":"2025-01-23 09:31:58.665312","email":"mlyons@gmail.com","first_name":"Edwin","has_logged_in":1,"id":8,"is_active":1,"is_staff":0,"is_superuser":0,"last_login":null,"last_name":"Rogers","membership":45484348,"membership_expiration":"2028-07-22","password":"pbkdf2_sha256$870000$GUblgD0GuKolRrS3Euq3oL$/ywpJfb5pP6yJYp0Tq0z2AVNF5sJmX6vsQzHBiXIqKQ=","postal_code":"14876","state_province":"Oregon","username":"mlyons@gmail.com"},{"address":"987 Hernandez Extensions","address2":"","birthday":"1988-08-05","city":"Johnsonchester","country":"United States","date_joined":"2025-01-23 09:31:58.668939","email":"lisasanders@peck.com","first_name":"Rebecca","has_logged_in":0,"id":9,"is_active":1,"is_staff":0,"is_superuser":0,"last_login":null,"last_name":"Peterson","membership":47156166,"membership_expiration":"2025-12-08","password":"pbkdf2_sha256$870000$d8XwUiLaXpUPCoWeLuG9W9$aolJEQm1rFgtL8WWtlo7sxHgTJOaPH+a/8DbEjJhZiU=","postal_code":"65689","state_province":"Washington","username":"lisasanders@peck.com"},{"address":"30482 Chang Loaf","address2":"","birthday":"1997-02-15","city":"Jaclynmouth","country":"Canada","date_joined":"2025-01-23 09:31:58.673065","email":"petersonjessica@walsh.com","first_name":"Amber","has_logged_in":0,"id":10,"is_active":1,"is_staff":0,"is_superuser":0,"last_login":null,"last_name":"Holmes","membership":80546750,"membership_expiration":"2027-12-27","password":"pbkdf2_sha256$870000$WTKMzdaf29s1y7eiWFIIDh$iJspNnhzOkdeM0GlzM9adZZu9WdoGKFG7OL3xht3Pck=","postal_code":"55267","state_province":"British Columbia","username":"petersonjessica@walsh.com"},{"address":"99448 Fuller Loop Apt. 546","address2":"","birthday":"1984-01-18","city":"Collinsstad","country":"United States","date_joined":"2025-01-23 09:31:58.676684","email":"emcknight@hansen.com","first_name":"Ruben","has_logged_in":0,"id":11,"is_active":1,"is_staff":0,"is_superuser":0,"last_login":null,"last_name":"Crawford","membership":31355746,"membership_expiration":"2025-09-29","password":"pbkdf2_sha256$870000$vLQkmdZ5feo0QhZjfO7wHX$opLxiueMI96oXefdr3zSH9c7A13pcw0ow5iuC0nRGzg=","postal_code":"46979","state_province":"Washington","username":"emcknight@hansen.com"},{"address":"50677 Vasquez Lake","address2":"","birthday":null,"city":"Barnettmouth","country":"United States","date_joined":"2025-01-23 09:31:58.680309","email":"lutzalexander@yahoo.com","first_name":"Madison","has_logged_in":0,"id":12,"is_active":1,"is_staff":0,"is_superuser":0,"last_login":null,"last_name":"King","membership":null,"membership_expiration":null,"password":"pbkdf2_sha256$870000$S3R1uAv60ePpvESnj5WPi1$vjUm680c1YN2FPoY2CRGOLlUMejwP63zwsrUfcHc5m0=","postal_code":"11548","state_province":"Washington","username":"lutzalexander@yahoo.com"},{"address":"14659 Roberson Ford","address2":"","birthday":"1992-02-07","city":"Wilsontown","country":"United States","date_joined":"2025-01-23 09:31:58.683927","email":"aaronthomas@hotmail.com","first_name":"James","has_logged_in":0,"id":13,"is_active":1,"is_staff":0,"is_superuser":0,"last_login":null,"last_name":"Young","membership":94720047,"membership_expiration":"2026-12-16","password":"pbkdf2_sha256$870000$S1JXRFtQXQ1ZWKC4J3Kn1D$0MXqsHQ4CqsQHKK1CCPzYwOsRYwcGAlZMII/msODWK0=","postal_code":"12021","state_province":"Washington","username":"aaronthomas@hotmail.com"},{"address":"72470 Antonio Rapids","address2":"","birthday":"2012-08-06","city":"Scottton","country":"United States","date_joined":"2025-01-23 09:31:58.688074","email":"cathy48@hotmail.com","first_name":"Justin","has_logged_in":0,"id":14,"is_active":1,"is_staff":0,"is_superuser":0,"last_login":null,"last_name":"Simon","membership":null,"membership_expiration":null,"password":"pbkdf2_sha256$870000$MJ9JTk0zJRMdMbdtfoh9JV$4ODBXav8K7886WNj1GMhl0G8EwoJ0ENanhkLy/rkA9Y=","postal_code":"14876","state_province":"Oregon","username":"cathy48@hotmail.com"},{"address":"4904 Richard Landing","address2":"","birthday":"2016-09-09","city":"Port Dawn","country":"Canada","date_joined":"2025-01-23 09:31:58.691689","email":"johnmiles@gmail.com","first_name":"Tiffany","has_logged_in":0,"id":15,"is_active":1,"is_staff":0,"is_superuser":0,"last_login":null,"last_name":"Baldwin","membership":null,"membership_expiration":null,"password":"pbkdf2_sha256$870000$y6R86EPWhrNs6S8JyWCwEw$uHllwq7IdQCkDSYdZPRYhgsau5qTHMK1W+9JDa2afAw=","postal_code":"65689","state_province":"British Columbia","username":"johnmiles@gmail.com"},{"address":"10043 Ponce Cliff","address2":"Apt. 553","birthday":"1996-03-15","city":"Toddhaven","country":"Canada","date_joined":"2025-01-23 09:31:58.695825","email":"benjaminwalsh@hudson-galvan.com","first_name":"Susan","has_logged_in":0,"id":16,"is_active":1,"is_staff":0,"is_superuser":0,"last_login":null,"last_name":"Smith","membership":94526151,"membership_expiration":"2026-01-13","password":"pbkdf2_sha256$870000$5DtcPjxN3HHvGW0azDNtpi$GgYheZ5K7I1kOjjuuHZ18GGvdDPCqm3OKefZ/KB6LXk=","postal_code":"55267","state_province":"British Columbia","username":"benjaminwalsh@hudson-galvan.com"},{"address":"072 Robert Mountains","address2":"","birthday":"1998-06-24","city":"Lake Aimeeburgh","country":"United States","date_joined":"2025-01-23 09:31:58.699988","email":"umcclure@ramirez.info","first_name":"Harry","has_logged_in":0,"id":17,"is_active":1,"is_staff":0,"is_superuser":0,"last_login":null,"last_name":"Gomez","membership":79880300,"membership_expiration":"2025-04-14","password":"pbkdf2_sha256$870000$UF2ISXvgICQpdfGtLFcWIv$MmGWBsxcacXAlAm4EcuVT5lIMLNcKPm7DZgMqnIzKBw=","postal_code":"46979","state_province":"Oregon","username":"umcclure@ramirez.info"},{"address":"910 James Valley","address2":"","birthday":"1983-07-08","city":"Castilloland","country":"Canada","date_joined":"2025-01-23 09:31:58.704286","email":"jacksonholly@gmail.com","first_name":"Cynthia","has_logged_in":0,"id":18,"is_active":1,"is_staff":0,"is_superuser":0,"last_login":null,"last_name":"Henderson","membership":19525019,"membership_expiration":"2026-10-20","password":"pbkdf2_sha256$870000$KigtMpjBsJZfcSwh659KB8$u22UFkQbt7eaVVaufM8nIR7Kz6rQY7KFCGjsZbkN4Bc=","postal_code":"11548","state_province":"British Columbia","username":"jacksonholly@gmail.com"},{"address":"12828 Krystal Fords","address2":"","birthday":"2000-09-30","city":"East Dale","country":"United States","date_joined":"2025-01-23 09:31:58.708397","email":"christine06@nguyen.org","first_name":"Spencer","has_logged_in":0,"id":19,"is_active":1,"is_staff":0,"is_superuser":0,"last_login":null,"last_name":"Russell","membership":83217423,"membership_expiration":"2026-10-18","password":"pbkdf2_sha256$870000$EWe0Qofl3RweEzGgEAc6wa$8gxZdKgjevfxRxhlk58yyP+j5qNvAE4bHybyG14bnS0=","postal_code":"12021","state_province":"Washington","username":"christine06@nguyen.org"},{"address":"938 Cantu Key Suite 632","address2":"","birthday":"1992-07-07","city":"Darylmouth","country":"United States","date_joined":"2025-01-23 09:31:58.712532","email":"pmcgee@brown-brandt.com","first_name":"Justin","has_logged_in":0,"id":20,"is_active":1,"is_staff":0,"is_superuser":0,"last_login":"2025-01-28 05:13:05.225428","last_name":"Howard","membership":null,"membership_expiration":null,"password":"pbkdf2_sha256$870000$LIyyNUtRQZ8VlhHGCORuLw$yBysGJ/oE1TmuoouAKUs/b47MnOfaZ8uU43XbrMEiQA=","postal_code":"14876","state_province":"Oregon","username":"pmcgee@brown-brandt.com"},{"address":"5289 Deborah Center Apt. 994","address2":"","birthday":"2000-05-30","city":"Walterview","country":"United States","date_joined":"2025-01-23 09:31:58.716473","email":"walkerjessica@hotmail.com","first_name":"Judy","has_logged_in":0,"id":21,"is_active":1,"is_staff":0,"is_superuser":0,"last_login":null,"last_name":"Alexander","membership":null,"membership_expiration":null,"password":"pbkdf2_sha256$870000$eEyYYWcFqLoeHWMwCyFLKU$pXC+fqojvHgMyCLF4dHDkQT/gjo9psvCm51LrGCYn5Y=","postal_code":"65689","state_province":"Oregon","username":"walkerjessica@hotmail.com"},{"address":"54905 Morales Canyon Suite 300","address2":"","birthday":null,"city":"Randyshire","country":"United States","date_joined":"2025-01-23 09:31:58.720098","email":"cooperjoel@yahoo.com","first_name":"Elizabeth","has_logged_in":0,"id":22,"is_active":1,"is_staff":0,"is_superuser":0,"last_login":null,"last_name":"Murray","membership":null,"membership_expiration":null,"password":"pbkdf2_sha256$870000$x1G3GBgkN5yIm5BhCVFdK3$lA0NISoSLngRTZHFpghm0PMvQ1KVdajtah9I/Mop7Ww=","postal_code":"55267","state_province":"Washington","username":"cooperjoel@yahoo.com"},{"address":"24872 Brown Overpass Apt. 191","address2":"","birthday":"1984-12-27","city":"South Markstad","country":"Canada","date_joined":"2025-01-23 09:31:58.724230","email":"maria25@gmail.com","first_name":"Renee","has_logged_in":0,"id":23,"is_active":1,"is_staff":0,"is_superuser":0,"last_login":null,"last_name":"Wright","membership":null,"membership_expiration":null,"password":"pbkdf2_sha256$870000$hybkx6t99sfFEiAAAh5038$w/5ZQ1fT9NfgbcUuo8Tf2CYm2VR4pR542DvjbTye/9Y=","postal_code":"46979","state_province":"British Columbia","username":"maria25@gmail.com"},{"address":"73688 Roger Road Suite 032","address2":"","birthday":"1988-11-18","city":"Samanthabury","country":"Canada","date_joined":"2025-01-23 09:31:58.728359","email":"jennifer14@lucas.com","first_name":"Frederick","has_logged_in":0,"id":24,"is_active":1,"is_staff":0,"is_superuser":0,"last_login":null,"last_name":"May","membership":32984947,"membership_expiration":"2027-01-28","password":"pbkdf2_sha256$870000$P5QWnFiJ7lc1wneMN0yEab$5svbvp9uHv03iKgwzRhsiqVfZxqikXYy8Ax9ZQuTi2o=","postal_code":"11548","state_province":"British Columbia","username":"jennifer14@lucas.com"},{"address":"38620 Andre Divide","address2":"","birthday":"1981-01-12","city":"West Nicole","country":"Canada","date_joined":"2025-01-23 09:31:58.731977","email":"kristinadavis@gmail.com","first_name":"Nathan","has_logged_in":0,"id":25,"is_active":1,"is_staff":0,"is_superuser":0,"last_login":null,"last_name":"Sullivan","membership":31913662,"membership_expiration":"2028-11-18","password":"pbkdf2_sha256$870000$Wtk29YCM3qcizKezizJrVE$Wp4uGE+EXy3bbnj+gntGvVfp/008FsxBHXVOgvi9KsY=","postal_code":"12021","state_province":"British Columbia","username":"kristinadavis@gmail.com"},{"address":"8053 Barbara Place Suite 843","address2":"Suite 760","birthday":null,"city":"West Tammy","country":"United States","date_joined":"2025-01-23 09:31:58.735580","email":"sandersduane@hotmail.com","first_name":"Brett","has_logged_in":0,"id":26,"is_active":1,"is_staff":0,"is_superuser":0,"last_login":null,"last_name":"Garza","membership":68907107,"membership_expiration":"2024-10-10","password":"pbkdf2_sha256$870000$AQTKne5CoKvYKEqpVeDkZ0$8vaM29LTmfUfHwBdojauwRuvnFijqO7mdEFkG31EKxU=","postal_code":"14876","state_province":"Washington","username":"sandersduane@hotmail.com"},{"address":"53516 Schmidt Skyway","address2":"Apt. 093","birthday":"2001-01-18","city":"Lake Barbaraberg","country":"United States","date_joined":"2025-01-23 09:31:58.739193","email":"cwhite@yahoo.com","first_name":"Theresa","has_logged_in":0,"id":27,"is_active":1,"is_staff":0,"is_superuser":0,"last_login":null,"last_name":"Castro","membership":56149296,"membership_expiration":"2026-11-16","password":"pbkdf2_sha256$870000$Egm3SImPxVd00Z9pctZthL$ZWPh/5ANPmDU+cY4YcSrOSh4Z3K1JLYvWt5bylKLKqg=","postal_code":"65689","state_province":"Washington","username":"cwhite@yahoo.com"},{"address":"3513 Teresa Lock Apt. 656","address2":"","birthday":"1989-05-27","city":"Williamburgh","country":"United States","date_joined":"2025-01-23 09:31:58.743330","email":"charleschase@parker.com","first_name":"Elizabeth","has_logged_in":0,"id":28,"is_active":1,"is_staff":0,"is_superuser":0,"last_login":null,"last_name":"Cole","membership":79100861,"membership_expiration":"2027-02-01","password":"pbkdf2_sha256$870000$CE7ahDYwsMwCqSwijiwNfW$vX0kNuUmEWsHefrCeg1n3WsfUUI6X8y0lY7ARiJ3hgw=","postal_code":"55267","state_province":"Oregon","username":"charleschase@parker.com"},{"address":"07281 Barrett Roads Apt. 634","address2":"","birthday":"2002-03-08","city":"Longmouth","country":"United States","date_joined":"2025-01-23 09:31:58.746949","email":"edwin97@yahoo.com","first_name":"Tyler","has_logged_in":0,"id":29,"is_active":1,"is_staff":0,"is_superuser":0,"last_login":null,"last_name":"Wagner","membership":51566283,"membership_expiration":"2028-12-04","password":"pbkdf2_sha256$870000$F2ENCmXfH8QtTI97xpSSsy$gIgrYKTceuWD5B6KQdEak/3r/c/U4lGe2m/4FS8oGwM=","postal_code":"46979","state_province":"Oregon","username":"edwin97@yahoo.com"},{"address":"1308 Combs Mountain","address2":"Apt. 895","birthday":"1999-02-22","city":"Jeffreymouth","country":"United States","date_joined":"2025-01-23 09:31:58.751068","email":"leonardgarcia@galloway.com","first_name":"Harold","has_logged_in":0,"id":30,"is_active":1,"is_staff":0,"is_superuser":0,"last_login":"2025-02-02 09:35:08.374774","last_name":"Snyder","membership":17111275,"membership_expiration":"2027-11-14","password":"pbkdf2_sha256$870000$Jf9eEiphVCIx8qsoTLCw60$1v9P5taNGR7vjv056KhQOCrlDk3Sl7hQCCCCE/MEuKE=","postal_code":"11548","state_province":"Washington","username":"leonardgarcia@galloway.com"}]